django_lucide_icons/__init__.py
django_lucide_icons/apps.py
django_lucide_icons/templatetags/__init__.py
django_lucide_icons/templatetags/lucide_tags.py
django_lucide_icons-0.2.2.dist-info/LICENSE
django_lucide_icons-0.2.2.dist-info/LICENSE.md
django_lucide_icons-0.2.2.dist-info/WHEEL
django_lucide_icons-0.2.2.dist-info/METADATA
django_lucide_icons-0.2.2.dist-info/RECORD
