Metadata-Version: 2.1
Name: django-lucide-icons
Version: 0.2.2
Summary: Django Lucide Icons
Author-email: Fabian Binz <fabian.binz@gmail.com>
Classifier: Development Status :: 5 - Production/Stable
Classifier: Environment :: Web Environment
Classifier: Framework :: Django
Classifier: Framework :: Django :: 3.2
Classifier: Framework :: Django :: 4.0
Classifier: Framework :: Django :: 4.1
Classifier: Intended Audience :: Developers
Classifier: License :: OSI Approved :: MIT License
Classifier: Natural Language :: English
Classifier: Operating System :: OS Independent
Classifier: Programming Language :: Python
Classifier: Programming Language :: Python :: 3
Classifier: Programming Language :: Python :: 3.8
Classifier: Programming Language :: Python :: 3.9
Classifier: Programming Language :: Python :: 3.10
Classifier: Topic :: Utilities
Requires-Dist: typer~=0.9 ; extra == "dev"
Requires-Dist: freezegun~=1.3 ; extra == "dev"
Requires-Dist: pytest-django~=4.7 ; extra == "dev"
Requires-Dist: pytest-mock~=3.12 ; extra == "dev"
Requires-Dist: coverage~=7.3 ; extra == "dev"
Requires-Dist: pre-commit~=3.5 ; extra == "dev"
Requires-Dist: ruff~=0.1.7 ; extra == "dev"
Requires-Dist: sphinx~=7.1 ; extra == "dev"
Requires-Dist: sphinx-rtd-theme~=2.0 ; extra == "dev"
Requires-Dist: m2r2==0.3.3.post2 ; extra == "dev"
Requires-Dist: mistune<2.0.0 ; extra == "dev"
Requires-Dist: flit~=3.9 ; extra == "dev"
Requires-Dist: ambient-package-update~=24.6.4 ; extra == "dev"
Project-URL: Bugtracker, https://github.com/ambient-innovation/django-lucide-icons/issues
Project-URL: Changelog, https://django-lucide-icons.readthedocs.io/en/latest/features/changelog.html
Project-URL: Documentation, https://django-lucide-icons.readthedocs.io/en/latest/index.html
Project-URL: Homepage, https://github.com/ambient-innovation/django-lucide-icons/
Project-URL: Maintained by, https://ambient.digital
Provides-Extra: dev
